nuvolos/__init__.py
nuvolos/sql_utils.py
nuvolos/version.py
nuvolos-0.6.5.dist-info/METADATA
nuvolos-0.6.5.dist-info/WHEEL
nuvolos-0.6.5.dist-info/top_level.txt
nuvolos-0.6.5.dist-info/RECORD
