Metadata-Version: 2.4
Name: nuvolos
Version: 0.6.5
Summary: The Nuvolos Python library for database connectivity
Author-email: Alphacruncher <support@nuvolos.cloud>
License: MIT
Project-URL: homepage, https://github.com/nuvolos-cloud/python-connector
Requires-Python: >=3.7
Requires-Dist: keyring>=24.1.0
Requires-Dist: snowflake-connector-python[pandas]>=3.15.0
Requires-Dist: snowflake-sqlalchemy>=1.7.3
Requires-Dist: cryptography>=44.0.0
Requires-Dist: pyarrow<19.0.0,>=18.1.0
Provides-Extra: test
Requires-Dist: pytest; extra == "test"
